win32more/Microsoft/Graphics/Canvas/__init__.py
win32more/Microsoft/Graphics/Canvas/Brushes/__init__.py
win32more/Microsoft/Graphics/Canvas/Effects/__init__.py
win32more/Microsoft/Graphics/Canvas/Geometry/__init__.py
win32more/Microsoft/Graphics/Canvas/Printing/__init__.py
win32more/Microsoft/Graphics/Canvas/Svg/__init__.py
win32more/Microsoft/Graphics/Canvas/Text/__init__.py
win32more/Microsoft/Graphics/Canvas/UI/__init__.py
win32more/Microsoft/Graphics/Canvas/UI/Composition/__init__.py
win32more/Microsoft/Graphics/Canvas/UI/Xaml/__init__.py
win32more/dll/arm64/Microsoft.Graphics.Canvas.dll
win32more/dll/x64/Microsoft.Graphics.Canvas.dll
win32more/dll/x86/Microsoft.Graphics.Canvas.dll
win32more_microsoft_graphics_win2d-0.8.1.3.2.dist-info/METADATA
win32more_microsoft_graphics_win2d-0.8.1.3.2.dist-info/WHEEL
win32more_microsoft_graphics_win2d-0.8.1.3.2.dist-info/RECORD
